state_mem.v
`define IDLE 2'b00
`define FETCH 2'b01
`define EXEC 2'b10
module state(clk, reset, run, halt, cs);
    input clk, reset, run, halt;
    output [1:0] cs;
    reg [1:0] cs;

    always @ (posedge clk or negedge reset)
    if (!reset) cs <= `IDLE;
    else
        case (cs)
            `IDLE: if(run) cs <= `FETCH;
            `FETCH: cs <= `EXEC;
            `EXEC: if(halt) cs <= `IDLE;
            else cs <= `FETCH;
            default: cs <= 2'bxx;
        endcase
endmodule

module mem3(clk, load, addr, d, q);
    parameter DWIDTH=16, AWIDTH=12, WORDS=4096;

    input clk, load;
    input [AWIDTH-1:0] addr;
    input [DWIDTH-1:0] d;
    output [DWIDTH-1:0] q;
    reg [DWIDTH-1:0] q;
    reg [DWIDTH-1:0] mem [WORDS-1:0];

    always @ (posedge clk)
        begin
            if (load) mem[addr] <= d;
            q <= mem[addr];
        end
    integer i;
    initial begin
        for(i=0;i<WORDS;i=i+1)
        mem[i] = i;
    end
endmodule


module state_mem(
    input clk,
    input reset,
    input run,
    input halt,
    output [15:0] out
);
    reg [11:0] addr;
    wire [1:0] cs;
    wire [15:0] mem_data;

    state state_inst(
        .clk(clk),
        .reset(reset),
        .run(run),
        .halt(halt),
        .cs(cs)
    );

    mem3 mem_inst(
        .clk(clk),
        .load(1'b0),
        .addr(addr),
        .d(16'b0),
        .q(mem_data)
    );

    always @(posedge clk or negedge reset) begin
        if (!reset)
            addr <= 12'b0;
        else if (cs == `EXEC)
            addr <= addr + 1;
    end

    assign out = (cs == `EXEC) ? (mem_data + 2) : 16'b0;

endmodule

module state_mem_sim;
    reg clk, reset, run, halt;
    wire [15:0] out;

    state_mem state_mem_inst(
        .clk(clk),
        .reset(reset),
        .run(run),
        .halt(halt),
        .out(out)
    );

    initial begin
        $dumpfile("state_mem.vcd");
        $dumpvars(0, state_mem_sim);
    end

    initial begin
        clk = 0; halt = 0; reset = 0; run = 0;
        #100 reset = 1; run = 1;
        #900 $finish;
    end

    always #50 clk = ~clk;
endmodule

state_mem.vcd
$date
	Sun Feb  2 21:18:43 2025
$end
$version
	Icarus Verilog
$end
$timescale
	1s
$end
$scope module state_mem_sim $end
$var wire 16 ! out [15:0] $end
$var reg 1 " clk $end
$var reg 1 # halt $end
$var reg 1 $ reset $end
$var reg 1 % run $end
$scope module state_mem_inst $end
$var wire 1 " clk $end
$var wire 1 # halt $end
$var wire 1 $ reset $end
$var wire 1 % run $end
$var wire 16 & out [15:0] $end
$var wire 16 ' mem_data [15:0] $end
$var wire 2 ( cs [1:0] $end
$var reg 12 ) addr [11:0] $end
$scope module mem_inst $end
$var wire 12 * addr [11:0] $end
$var wire 1 " clk $end
$var wire 16 + d [15:0] $end
$var wire 1 , load $end
$var parameter 32 - AWIDTH $end
$var parameter 32 . DWIDTH $end
$var parameter 32 / WORDS $end
$var reg 16 0 q [15:0] $end
$var integer 32 1 i [31:0] $end
$upscope $end
$scope module state_inst $end
$var wire 1 " clk $end
$var wire 1 # halt $end
$var wire 1 $ reset $end
$var wire 1 % run $end
$var reg 2 2 cs [1:0] $end
$upscope $end
$upscope $end
$upscope $end
$enddefinitions $end
$comment Show the parameter values. $end
$dumpall
b1000000000000 /
b10000 .
b1100 -
$end
#0
$dumpvars
b0 2
b1000000000000 1
bx 0
0,
b0 +
b0 *
b0 )
b0 (
bx '
b0 &
0%
0$
0#
0"
b0 !
$end
#50
b0 '
b0 0
1"
#100
0"
1%
1$
#150
b1 (
b1 2
1"
#200
0"
#250
b10 !
b10 &
b10 (
b10 2
1"
#300
0"
#350
b0 !
b0 &
b1 (
b1 2
b1 )
b1 *
1"
#400
0"
#450
b11 !
b11 &
b1 '
b1 0
b10 (
b10 2
1"
#500
0"
#550
b0 !
b0 &
b1 (
b1 2
b10 )
b10 *
1"
#600
0"
#650
b100 !
b100 &
b10 '
b10 0
b10 (
b10 2
1"
#700
0"
#750
b0 !
b0 &
b1 (
b1 2
b11 )
b11 *
1"
#800
0"
#850
b101 !
b101 &
b11 '
b11 0
b10 (
b10 2
1"
#900
0"
#950
b0 !
b0 &
b1 (
b1 2
b100 )
b100 *
1"
