test/memory/mem.v
module mem(clk, load, addr, d, q);
    input clk, load;
    input [15:0] addr, d;
    output [15:0] q;
    reg [15:0] q;
    reg [15:0] mem [4095:0];

    always @ (posedge clk)
        begin
            if (load) mem[addr] <= d;
            q <= mem[addr];
        end
endmodule

module mem_sim;
    reg clk, load;
    reg [15:0] addr, d;
    wire [15:0] q;

    mem m(clk, load, addr, d, q);

    initial begin
        $dumpfile("mem.vcd");
        $dumpvars(0, mem_sim);
    end

    initial begin
        clk = 0;
        forever #5 clk = ~clk;
    end

    initial begin
        load = 1; addr = 1; d = 23;
        #100 load = 0; addr = 0;
        #100 addr = 1; d = 1;
        #100 load = 1; addr = 1; d = 2;
        #100 load = 0; addr = 1;
        #100 $finish;
    end

endmodule

test/memory/mem.vcd
$date
	Sun Feb  2 21:00:45 2025
$end
$version
	Icarus Verilog
$end
$timescale
	1s
$end
$scope module mem_sim $end
$var wire 16 ! q [15:0] $end
$var reg 16 " addr [15:0] $end
$var reg 1 # clk $end
$var reg 16 $ d [15:0] $end
$var reg 1 % load $end
$scope module m $end
$var wire 16 & addr [15:0] $end
$var wire 1 # clk $end
$var wire 16 ' d [15:0] $end
$var wire 1 % load $end
$var reg 16 ( q [15:0] $end
$upscope $end
$upscope $end
$enddefinitions $end
$comment Show the parameter values. $end
$dumpall
$end
#0
$dumpvars
bx (
b10111 '
b1 &
1%
b10111 $
0#
b1 "
bx !
$end
#5
1#
#10
0#
#15
b10111 !
b10111 (
1#
#20
0#
#25
1#
#30
0#
#35
1#
#40
0#
#45
1#
#50
0#
#55
1#
#60
0#
#65
1#
#70
0#
#75
1#
#80
0#
#85
1#
#90
0#
#95
1#
#100
0#
b0 "
b0 &
0%
#105
bx !
bx (
1#
#110
0#
#115
1#
#120
0#
#125
1#
#130
0#
#135
1#
#140
0#
#145
1#
#150
0#
#155
1#
#160
0#
#165
1#
#170
0#
#175
1#
#180
0#
#185
1#
#190
0#
#195
1#
#200
0#
b1 $
b1 '
b1 "
b1 &
#205
b10111 !
b10111 (
1#
#210
0#
#215
1#
#220
0#
#225
1#
#230
0#
#235
1#
#240
0#
#245
1#
#250
0#
#255
1#
#260
0#
#265
1#
#270
0#
#275
1#
#280
0#
#285
1#
#290
0#
#295
1#
#300
0#
b10 $
b10 '
1%
#305
1#
#310
0#
#315
b10 !
b10 (
1#
#320
0#
#325
1#
#330
0#
#335
1#
#340
0#
#345
1#
#350
0#
#355
1#
#360
0#
#365
1#
#370
0#
#375
1#
#380
0#
#385
1#
#390
0#
#395
1#
#400
0#
0%
