test/state_watch/state_watch.v
`define NORMAL 2'b00
`define SEC 2'b01
`define MIN 2'b10
`define HOUR 2'b11

module state_watch(clk, reset, SW1, SW2, SW3, cs, sec_reset, min_inc, hour_inc);
    input clk, reset, SW1, SW2, SW3;
    output reg [1:0] cs;
    output sec_reset, min_inc, hour_inc;

    always @(posedge clk or negedge reset)
        if (!reset) cs <= `NORMAL;
        else
            case (cs)
                `NORMAL: 
                if (SW2)
                    cs <= `SEC;
                else
                    cs <= `NORMAL;
                `SEC:
                if (SW2)
                    cs <= `NORMAL;
                else if (SW3)
                    cs <= `HOUR;
                else
                    cs <= `SEC;
                `HOUR:
                if (SW2)
                    cs <= `NORMAL;
                else if (SW3)
                    cs <= `MIN;
                else
                    cs <= `HOUR;
                `MIN:
                if (SW2)
                    cs <= `NORMAL;
                else if (SW3)
                    cs <= `SEC;
                else
                    cs <= `MIN;
                default:
                    cs <= 2'bxx;
            endcase
    assign sec_reset = (cs == `SEC) && SW1;
    assign min_inc = (cs == `MIN) && SW1;
    assign hour_inc = (cs == `HOUR) && SW1;
endmodule

module state_watch_sim;
    reg clk, reset, SW1, SW2, SW3;
    wire [1:0] cs;
    wire sec_reset, min_inc, hour_inc;

    state_watch state_watch_inst(clk, reset, SW1, SW2, SW3, cs, sec_reset, min_inc, hour_inc);

    initial begin
        $dumpfile("state_watch.vcd");
        $dumpvars(0, state_watch_sim);
    end

    initial begin
        clk = 0;
        forever #11 clk = ~clk;
    end

    initial begin
        reset = 0;
        SW1 = 0;
        SW2 = 0;
        SW3 = 0;
        #100 reset = 1;
        #100 SW2 = 1;
        #30 SW2 = 0;
        #100 SW3 = 1;
        #30 SW3 = 0;
        #100 SW3 = 1;
        #30 SW3 = 0;
        #100 SW3 = 1; 
        #30 SW3 = 0;
        #100 SW1 = 1;
        #100 $finish;
    end

endmodule

test/state_watch/state_watch.vcd
$date
	Sun Feb  2 20:50:47 2025
$end
$version
	Icarus Verilog
$end
$timescale
	1s
$end
$scope module state_watch_sim $end
$var wire 1 ! sec_reset $end
$var wire 1 " min_inc $end
$var wire 1 # hour_inc $end
$var wire 2 $ cs [1:0] $end
$var reg 1 % SW1 $end
$var reg 1 & SW2 $end
$var reg 1 ' SW3 $end
$var reg 1 ( clk $end
$var reg 1 ) reset $end
$scope module state_watch_inst $end
$var wire 1 % SW1 $end
$var wire 1 & SW2 $end
$var wire 1 ' SW3 $end
$var wire 1 ( clk $end
$var wire 1 # hour_inc $end
$var wire 1 " min_inc $end
$var wire 1 ) reset $end
$var wire 1 ! sec_reset $end
$var reg 2 * cs [1:0] $end
$upscope $end
$upscope $end
$enddefinitions $end
$comment Show the parameter values. $end
$dumpall
$end
#0
$dumpvars
b0 *
0)
0(
0'
0&
0%
b0 $
0#
0"
0!
$end
#11
1(
#22
0(
#33
1(
#44
0(
#55
1(
#66
0(
#77
1(
#88
0(
#99
1(
#100
1)
#110
0(
#121
1(
#132
0(
#143
1(
#154
0(
#165
1(
#176
0(
#187
1(
#198
0(
#200
1&
#209
b1 $
b1 *
1(
#220
0(
#230
0&
#231
1(
#242
0(
#253
1(
#264
0(
#275
1(
#286
0(
#297
1(
#308
0(
#319
1(
#330
0(
1'
#341
b11 $
b11 *
1(
#352
0(
#360
0'
#363
1(
#374
0(
#385
1(
#396
0(
#407
1(
#418
0(
#429
1(
#440
0(
#451
1(
#460
1'
#462
0(
#473
b10 $
b10 *
1(
#484
0(
#490
0'
#495
1(
#506
0(
#517
1(
#528
0(
#539
1(
#550
0(
#561
1(
#572
0(
#583
1(
#590
1'
#594
0(
#605
b1 $
b1 *
1(
#616
0(
#620
0'
#627
1(
#638
0(
#649
1(
#660
0(
#671
1(
#682
0(
#693
1(
#704
0(
#715
1(
#720
1!
1%
