test/state/state.v
`define IDLE 2'b00
`define FETCH 2'b01
`define EXEC 2'b10

module state(clk, reset, run, halt, cs);
    input clk, reset, run, halt;
    output reg [1:0] cs;

    always @ (posedge clk or negedge reset)
        if (!reset) cs <= `IDLE;
        else
            case (cs)
                `IDLE: if(run) cs <= `FETCH;
                `FETCH: cs <= `EXEC;
                `EXEC: if (halt) cs <= `IDLE;
                else cs <= `FETCH;
                default: cs <= 2'bxx;
            endcase
endmodule

module state_sim;
    reg clk, reset, run, halt;
    wire [1:0] cs;

    state state_inst(clk, reset, run, halt, cs);

    initial begin
        $dumpfile("state.vcd");
        $dumpvars(0, state_sim);
    end

    initial begin
        clk = 0;
        forever #50 clk = ~clk;
    end

    initial begin
        reset = 0;
        run = 0;
        halt = 0;
        #100 reset = 1;
        #100 run = 1;
        #100 run = 0;
        #100 halt = 1;
        #100 halt = 0;
        #100 $finish;
    end
endmodule

test/state/state.vcd
$date
	Sun Feb  2 20:17:39 2025
$end
$version
	Icarus Verilog
$end
$timescale
	1s
$end
$scope module state_sim $end
$var wire 2 ! cs [1:0] $end
$var reg 1 " clk $end
$var reg 1 # halt $end
$var reg 1 $ reset $end
$var reg 1 % run $end
$scope module state_inst $end
$var wire 1 " clk $end
$var wire 1 # halt $end
$var wire 1 $ reset $end
$var wire 1 % run $end
$var reg 2 & cs [1:0] $end
$upscope $end
$upscope $end
$enddefinitions $end
$comment Show the parameter values. $end
$dumpall
$end
#0
$dumpvars
b0 &
0%
0$
0#
0"
b0 !
$end
#50
1"
#100
0"
1$
#150
1"
#200
0"
1%
#250
b1 !
b1 &
1"
#300
0"
0%
#350
b10 !
b10 &
1"
#400
0"
1#
#450
b0 !
b0 &
1"
#500
0"
0#
