test/fulladder/fulladder.v
module fulladder(a, b, cin, s, cout);
    input a, b, cin;
    output s, cout;

    assign s = a ^ b ^ cin;
    assign cout = (a & b) | (b & cin) | (cin & a);

endmodule

module fulladder_sim;
    reg a, b, cin;
    wire s, cout;

    fulladder fa(a,b,cin,s,cout);

    initial begin
        $dumpfile("fulladder.vcd");
        $dumpvars(0, fulladder_sim);
    end

    initial begin
        a = 0; b = 0; cin = 0;
        #100 cin = 1;
        #100 cin = 0; b = 1;
        #100 cin = 1;
        #100 a = 1; b = 0; cin = 0;
        #100 cin = 1;
        #100 cin = 0; b = 1;
        #100 cin = 1;
        #100 $finish;
    end

endmodule

test/fulladder/fulladder.vcd
$date
	Sun Feb  2 14:51:17 2025
$end
$version
	Icarus Verilog
$end
$timescale
	1s
$end
$scope module fulladder_sim $end
$var wire 1 ! s $end
$var wire 1 " cout $end
$var reg 1 # a $end
$var reg 1 $ b $end
$var reg 1 % cin $end
$scope module fa $end
$var wire 1 # a $end
$var wire 1 $ b $end
$var wire 1 % cin $end
$var wire 1 " cout $end
$var wire 1 ! s $end
$upscope $end
$upscope $end
$enddefinitions $end
$comment Show the parameter values. $end
$dumpall
$end
#0
$dumpvars
0%
0$
0#
0"
0!
$end
#100
1!
1%
#200
1!
1$
0%
#300
1"
0!
1%
#400
0"
1!
0%
0$
1#
#500
1"
0!
1%
#600
1"
0!
1$
0%
#700
1!
1%
