test/fulladder2/fulladder2.v
module halfadder(a,b,s,c);
    input a, b;
    output s, c;

    assign s = a ^ b;
    assign c = a & b;

endmodule

module fulladder2(a,b,cin,s,cout);
    input a, b, cin;
    output s, cout;
    wire s1, c1, c2;

    halfadder ha1(a,b,s1,c1);
    halfadder ha2(s1,cin,s,c2);

    assign cout = c1 | c2;

endmodule

module fulladder2_sim;
    reg a, b, cin;
    wire s, cout;

    fulladder2 fa(a,b,cin,s,cout);

    initial begin
        $dumpfile("fulladder2.vcd");
        $dumpvars(0, fulladder2_sim);
    end

    initial begin
        a = 0; b = 0; cin = 0;
        #100 cin = 1;
        #100 cin = 0; b = 1;
        #100 cin = 1;
        #100 a = 1; b = 0; cin = 0;
        #100 cin = 1;
        #100 cin = 0; b = 1;
        #100 cin = 1;
        #100 $finish;
    end

endmodule

test/fulladder2/fulladder2.vcd
$date
	Sun Feb  2 14:57:04 2025
$end
$version
	Icarus Verilog
$end
$timescale
	1s
$end
$scope module fulladder2_sim $end
$var wire 1 ! s $end
$var wire 1 " cout $end
$var reg 1 # a $end
$var reg 1 $ b $end
$var reg 1 % cin $end
$scope module fa $end
$var wire 1 # a $end
$var wire 1 $ b $end
$var wire 1 % cin $end
$var wire 1 " cout $end
$var wire 1 & s1 $end
$var wire 1 ! s $end
$var wire 1 ' c2 $end
$var wire 1 ( c1 $end
$scope module ha1 $end
$var wire 1 # a $end
$var wire 1 $ b $end
$var wire 1 ( c $end
$var wire 1 & s $end
$upscope $end
$scope module ha2 $end
$var wire 1 & a $end
$var wire 1 % b $end
$var wire 1 ' c $end
$var wire 1 ! s $end
$upscope $end
$upscope $end
$upscope $end
$enddefinitions $end
$comment Show the parameter values. $end
$dumpall
$end
#0
$dumpvars
0(
0'
0&
0%
0$
0#
0"
0!
$end
#100
1!
1%
#200
1&
1!
1$
0%
#300
1"
0!
1'
1%
#400
0"
1!
0'
0%
0$
1#
#500
1"
0!
1'
1%
#600
0&
1(
0!
0'
1$
0%
#700
1!
1%
